[
  {
    "href": "https://rewards.dicedreams.com/?handler=reward&link=treasurechelle230125",
    "date": "2025-01-25"
  },
  {
    "href": "https://rewards.dicedreams.com/?handler=reward&link=countthecookies220125",
    "date": "2025-01-25"
  },
  {
    "href": "https://rewards.dicedreams.com/?handler=reward&link=2mfollowers190125",
    "date": "2025-01-20"
  },
  {
    "href": "https://rewards.dicedreams.com/?handler=reward&link=3daysleftforpet180125",
    "date": "2025-01-19"
  },
  {
    "href": "https://rewards.dicedreams.com/?handler=reward&link=adoptionweekend170125",
    "date": "2025-01-19"
  },
  {
    "href": "https://rewards.dicedreams.com/?handler=reward&link=spotthedifference150125",
    "date": "2025-01-18"
  },
  {
    "href": "https://rewards.dicedreams.com/?handler=reward&link=newalbum140125",
    "date": "2025-01-18"
  },
  {
    "href": "https://rewards.dicedreams.com/?handler=reward&link=Albumlastday29302094",
    "date": "2025-01-18"
  },
  {
    "href": "https://rewards.dicedreams.com/?handler=reward&link=wildtrail110125",
    "date": "2025-01-18"
  },
  {
    "href": "https://rewards.dicedreams.com/?handler=reward&link=albumfinaldays090125",
    "date": "2025-01-18"
  },
  {
    "href": "https://rewards.dicedreams.com/?handler=reward&link=wordpuzzle080125",
    "date": "2025-01-18"
  },
  {
    "href": "https://rewards.dicedreams.com/?handler=reward&link=clockchallenge060125",
    "date": "2025-01-18"
  },
  {
    "href": "https://rewards.dicedreams.com/?handler=reward&link=dreambigtrail030125",
    "date": "2025-01-18"
  },
  {
    "href": "https://rewards.dicedreams.com/?handler=reward&link=triviatime020125",
    "date": "2025-01-18"
  },
  {
    "href": "https://rewards.dicedreams.com/?handler=reward&link=happynewyear010125",
    "date": "2025-01-18"
  },
  {
    "href": "https://rewards.dicedreams.com/?handler=reward&link=70kfollowers_311224",
    "date": "2025-01-18"
  },
  {
    "href": "https://rewards.dicedreams.com/?handler=reward&link=Samuelmovie291224a",
    "date": "2025-01-18"
  },
  {
    "href": "https://rewards.dicedreams.com/?handler=reward&link=pixieslastday291224",
    "date": "2025-01-18"
  },
  {
    "href": "https://rewards.dicedreams.com/?handler=reward&link=Pixieslastdaybroad281224",
    "date": "2025-01-18"
  },
  {
    "href": "https://rewards.dicedreams.com/?handler=reward&link=santaspuzzle261224",
    "date": "2025-01-18"
  },
  {
    "href": "https://d10x.co/dicedrems/giq6jVktu",
    "date": "2025-01-18"
  },
  {
    "href": "https://d10x.co/dicedrems/giqVyOoiP",
    "date": "2025-01-18"
  },
  {
    "href": "https://d10x.co/dicedrems/giqaBaX3v",
    "date": "2025-01-18"
  },
  {
    "href": "https://d10x.co/dicedrems/giqIeQoXt",
    "date": "2025-01-18"
  },
  {
    "href": "https://d10x.co/dicedrems/giqUmxKFf",
    "date": "2025-01-18"
  },
  {
    "href": "https://rewards.dicedreams.com/?handler=reward&link=fridaythe13th131224",
    "date": "2025-01-18"
  },
  {
    "href": "https://rewards.dicedreams.com/?handler=reward&link=cookieschallenge111224",
    "date": "2025-01-18"
  },
  {
    "href": "https://rewards.dicedreams.com/?handler=reward&link=Newalbumholiday101224",
    "date": "2025-01-18"
  },
  {
    "href": "https://d10x.co/dicedrems/giqcMU8Xp",
    "date": "2025-01-18"
  },
  {
    "href": "https://d10x.co/dicedrems/giq17Lhp4",
    "date": "2025-01-18"
  },
  {
    "href": "https://d10x.co/dicedrems/giqYUNVhT",
    "date": "2025-01-18"
  },
  {
    "href": "https://rewards.dicedreams.com/?handler=reward&link=cybermonday021224",
    "date": "2025-01-18"
  },
  {
    "href": "https://rewards.dicedreams.com/?handler=reward&link=BlackFridaytrail301124",
    "date": "2025-01-18"
  },
  {
    "href": "https://rewards.dicedreams.com/?handler=reward&link=blackfriday281124",
    "date": "2025-01-18"
  },
  {
    "href": "https://rewards.dicedreams.com/?handler=reward&link=blackfridaychallenge281124",
    "date": "2025-01-18"
  },
  {
    "href": "https://rewards.dicedreams.com/?handler=reward&link=VIP_bonus_201124",
    "date": "2025-01-18"
  },
  {
    "href": "https://d10x.co/dicedrems/giq5jduds",
    "date": "2025-01-18"
  },
  {
    "href": "https://d10x.co/dicedrems/giqpHKxRt",
    "date": "2025-01-18"
  },
  {
    "href": "https://d10x.co/dicedrems/giqdNjTBw",
    "date": "2025-01-18"
  },
  {
    "href": "https://d10x.co/dicedrems/giqA904By",
    "date": "2025-01-18"
  },
  {
    "href": "https://d10x.co/dicedrems/giqbjQ002",
    "date": "2025-01-18"
  },
  {
    "href": "https://d10x.co/dicedrems/giqRIfz73",
    "date": "2025-01-18"
  },
  {
    "href": "https://d10x.co/dicedrems/giqozA7qP",
    "date": "2025-01-18"
  },
  {
    "href": "https://d10x.co/dicedrems/giqEy2BUL",
    "date": "2025-01-18"
  },
  {
    "href": "https://d10x.co/dicedrems/giq6H4qq7",
    "date": "2025-01-18"
  },
  {
    "href": "https://d10x.co/dicedrems/giqA5Bp11",
    "date": "2025-01-18"
  },
  {
    "href": "https://d10x.co/dicedrems/giqdXGRjl?device_id=4436b341-b0bb-4abc-a6c6-8a6880233433",
    "date": "2025-01-18"
  },
  {
    "href": "https://rewards.dicedreams.com/?handler=reward&link=3lastdaysofdemon301024",
    "date": "2025-01-18"
  },
  {
    "href": "https://d10x.co/dicedrems/giqEp8SG8",
    "date": "2025-01-18"
  },
  {
    "href": "https://rewards.dicedreams.com/?handler=reward&link=guessthemovie311024",
    "date": "2025-01-18"
  },
  {
    "href": "https://d10x.co/dicedrems/giqtOtLE2",
    "date": "2025-01-18"
  },
  {
    "href": "https://rewards.dicedreams.com/?handler=reward&link=followus301024",
    "date": "2025-01-18"
  },
  {
    "href": "https://rewards.dicedreams.com/?handler=reward&link=pixiechallenge291024",
    "date": "2025-01-18"
  },
  {
    "href": "https://d10x.co/dicedrems/giqWDRDo7",
    "date": "2025-01-18"
  },
  {
    "href": "https://d10x.co/dicedrems/giqEnBdWr",
    "date": "2025-01-18"
  },
  {
    "href": "https://rewards.dicedreams.com/?handler=reward&link=hauntedtrail261024aaa",
    "date": "2025-01-18"
  },
  {
    "href": "https://d10x.co/dicedrems/giqCEDYCt",
    "date": "2025-01-18"
  },
  {
    "href": "https://d10x.co/dicedrems/giqhoUdPf",
    "date": "2025-01-18"
  },
  {
    "href": "https://d10x.co/dicedrems/giqXNKh3e",
    "date": "2025-01-18"
  },
  {
    "href": "https://d10x.co/dicedrems/giqHj7iFJ",
    "date": "2025-01-18"
  },
  {
    "href": "https://rewards.dicedreams.com/?handler=reward&link=Wickedtrail231024",
    "date": "2025-01-18"
  },
  {
    "href": "https://d10x.co/dicedrems/giqSKSuNR",
    "date": "2025-01-18"
  },
  {
    "href": "https://rewards.dicedreams.com/?handler=reward&link=neweicked221024",
    "date": "2025-01-18"
  },
  {
    "href": "https://d10x.co/dicedrems/giq8F6Mkk",
    "date": "2025-01-18"
  },
  {
    "href": "https://rewards.dicedreams.com/?handler=reward&link=2lastdaysofzebra201024",
    "date": "2025-01-18"
  },
  {
    "href": "https://d10x.co/dicedrems/giqBkVohe",
    "date": "2025-01-18"
  },
  {
    "href": "https://d10x.co/dicedrems/giqSVtPog",
    "date": "2025-01-18"
  },
  {
    "href": "https://rewards.dicedreams.com/?handler=reward&link=pettreatsale181024aaa",
    "date": "2025-01-18"
  },
  {
    "href": "https://rewards.dicedreams.com/?handler=reward&link=zebrachallenge161024",
    "date": "2025-01-18"
  },
  {
    "href": "https://rewards.dicedreams.com/?handler=reward&link=puzzlepet161024",
    "date": "2025-01-18"
  },
  {
    "href": "https://rewards.dicedreams.com/?handler=reward&link=Zebralastweek151024aa",
    "date": "2025-01-18"
  },
  {
    "href": "https://rewards.dicedreams.com/?handler=reward&link=foodchallenge131024",
    "date": "2025-01-18"
  },
  {
    "href": "https://d10x.co/dicedrems/giqeV2lpR",
    "date": "2025-01-18"
  },
  {
    "href": "https://rewards.dicedreams.com/?handler=reward&link=supermarkettrail121024",
    "date": "2025-01-18"
  },
  {
    "href": "https://d10x.co/dicedrems/giqfCdXxS",
    "date": "2025-01-18"
  },
  {
    "href": "https://d10x.co/dicedrems/giqLVUc1s",
    "date": "2025-01-18"
  },
  {
    "href": "https://d10x.co/dicedrems/giqN2OaUh",
    "date": "2025-01-18"
  },
  {
    "href": "https://d10x.co/dicedrems/giqhXDSH0",
    "date": "2025-01-18"
  },
  {
    "href": "https://rewards.dicedreams.com/?handler=reward&link=3daysleft_wow0510",
    "date": "2025-01-18"
  },
  {
    "href": "https://rewards.dicedreams.com/?handler=reward&link=3daysleft_wow0510broadcast",
    "date": "2025-01-18"
  },
  {
    "href": "https://rewards.dicedreams.com/?handler=reward&link=superpowers_0110",
    "date": "2025-01-18"
  },
  {
    "href": "https://rewards.dicedreams.com/?handler=reward&link=Lastweekofalbum011024",
    "date": "2025-01-18"
  },
  {
    "href": "https://d10x.co/dicedrems/giqDmndjy",
    "date": "2025-01-18"
  },
  {
    "href": "https://rewards.dicedreams.com/?handler=reward&link=SUPER_WEEKEND_2709",
    "date": "2025-01-18"
  },
  {
    "href": "https://rewards.dicedreams.com/?handler=reward&link=IOS_YES_2409",
    "date": "2025-01-18"
  },
  {
    "href": "https://rewards.dicedreams.com/?handler=reward&link=Pixies_last_day_yayyay2309",
    "date": "2025-01-18"
  },
  {
    "href": "https://rewards.dicedreams.com/?handler=reward&link=c0920cd",
    "date": "2025-01-18"
  },
  {
    "href": "https://rewards.dicedreams.com/?handler=reward&link=VIP_dynamo_170924",
    "date": "2025-01-18"
  },
  {
    "href": "https://rewards.dicedreams.com/?handler=reward&link=c0918lo",
    "date": "2025-01-18"
  },
  {
    "href": "https://rewards.dicedreams.com/?handler=reward&link=c0916sd",
    "date": "2025-01-18"
  },
  {
    "href": "https://rewards.dicedreams.com/?handler=reward&link=dynbr_0916sd",
    "date": "2025-01-18"
  },
  {
    "href": "https://rewards.dicedreams.com/?handler=reward&link=dynbr_0915cb",
    "date": "2025-01-18"
  },
  {
    "href": "https://rewards.dicedreams.com/?handler=reward&link=dynbr_0914as",
    "date": "2025-01-18"
  },
  {
    "href": "https://rewards.dicedreams.com/?handler=reward&link=is_0913px",
    "date": "2025-01-18"
  },
  {
    "href": "https://rewards.dicedreams.com/?handler=reward&link=c0912re",
    "date": "2025-01-18"
  },
  {
    "href": "https://rewards.dicedreams.com/?handler=reward&link=tx_0910we",
    "date": "2025-01-18"
  },
  {
    "href": "https://rewards.dicedreams.com/?handler=reward&link=c0910cb",
    "date": "2025-01-18"
  },
  {
    "href": "https://rewards.dicedreams.com/?handler=reward&link=c0909hg",
    "date": "2025-01-18"
  },
  {
    "href": "https://rewards.dicedreams.com/?handler=reward&link=is_0908as",
    "date": "2025-01-18"
  },
  {
    "href": "https://rewards.dicedreams.com/?handler=reward&link=dynbr_0906we",
    "date": "2025-01-18"
  }
]